pycorex/__init__.py
pycorex/gemini_client.py
pycorex/imagen_client.py
pycorex/uwgen_client.py
pycorex/configs/app_init.py
pycorex/configs/pycorex.py
pycorex/core/base_ai_client.py
pycorex/exceptions/api_error.py
pycorex/exceptions/no_candidates_error.py
pycorex/models/gemini.py
pycorex/models/prompt.py
pycorex/models/uwgen.py
pycorex/models/vertexai.py
pycorex-1.0.10.dist-info/METADATA
pycorex-1.0.10.dist-info/WHEEL
pycorex-1.0.10.dist-info/top_level.txt
pycorex-1.0.10.dist-info/RECORD
