Metadata-Version: 2.4
Name: pycorex
Version: 1.0.10
Summary: A lightweight Python core package for unified AI API access, designed for flexibility and scalability.
Author-email: kaioman <kajin0318@gmail.com>
Project-URL: Homepage, https://github.com/kaioman/pycorex
Project-URL: Repository, https://github.com/kaioman/pycorex
Project-URL: Issues, https://github.com/kaioman/pycorex/issues
Requires-Dist: libcore-hng
Requires-Dist: google-generativeai
Requires-Dist: tiktoken
Requires-Dist: google-cloud-aiplatform
Requires-Dist: pillow
Requires-Dist: psutil
